{
  "openapi": "3.1.0",
  "info": {
    "version": "1.0.0",
    "title": "Blog API",
    "license": {
      "name": "Apache 2.0",
      "url": "http://www.apache.org/licenses/LICENSE-2.0.html"
    },
    "description": "API for the travell app"
  },
  "servers": [
    {
      "url": "http://localhost:3000/api",
      "description": "Local server"
    },
    {
      "url": "https://travel-app-backend-9pto.onrender.com",
      "description": "server on render.com"
    }
  ],
  "tags": [
    {
      "name": "Auth",
      "description": "User registration, login, logout, and session refresh"
    },
    {
      "name": "Users",
      "description": "User profiles, avatars, and saved articles"
    },
    {
      "name": "Stories",
      "description": "Stories (posting, editing, deleting, filtering)"
    },
    {
      "name": "Categories",
      "description": "Story categories with pagination"
    }
  ],
  "paths": {
    "/auth/register": {
      "post": {
        "tags": [
          "Auth"
        ],
        "summary": "Register a new user",
        "description": "Creates a new user account",
        "operationId": "Register",
        "security": [
          {
            "bearerAuth": []
          }
        ],
        "requestBody": {
          "required": true,
          "content": {
            "application/json": {
              "schema": {
                "type": "object",
                "required": [
                  "name",
                  "email",
                  "password"
                ],
                "properties": {
                  "name": {
                    "type": "string",
                    "example": "Anton"
                  },
                  "email": {
                    "type": "string",
                    "example": "anton@example.com"
                  },
                  "password": {
                    "type": "string",
                    "example": "qwerty123"
                  }
                }
              }
            }
          }
        },
        "responses": {
          "201": {
            "description": "Successfully registered a user!",
            "content": {
              "application/json": {
                "schema": {
                  "type": "object",
                  "required": [
                    "status",
                    "message",
                    "data"
                  ],
                  "properties": {
                    "status": {
                      "type": "integer",
                      "example": 201
                    },
                    "message": {
                      "type": "string",
                      "example": "Successfully registered a user!"
                    },
                    "data": {
                      "$ref": "#/components/schemas/user"
                    }
                  }
                }
              }
            }
          },
          "400": {
            "$ref": "#/components/responses/400"
          },
          "500": {
            "$ref": "#/components/responses/500"
          }
        }
      }
    },
    "/auth/login": {
      "post": {
        "tags": [
          "Auth"
        ],
        "summary": "Login user",
        "description": "Login with email and password",
        "operationId": "Login",
        "security": [
          {
            "bearerAuth": []
          }
        ],
        "requestBody": {
          "required": true,
          "content": {
            "application/json": {
              "schema": {
                "type": "object",
                "required": [
                  "email",
                  "password"
                ],
                "properties": {
                  "email": {
                    "type": "string",
                    "example": "user@example.com"
                  },
                  "password": {
                    "type": "string",
                    "example": "qwerty123"
                  }
                }
              }
            }
          }
        },
        "responses": {
          "200": {
            "description": "Successfully logged in",
            "content": {
              "application/json": {
                "schema": {
                  "type": "object",
                  "required": [
                    "status",
                    "message",
                    "data"
                  ],
                  "properties": {
                    "status": {
                      "type": "integer",
                      "example": 200
                    },
                    "message": {
                      "type": "string",
                      "example": "Successfully logged in"
                    },
                    "data": {
                      "type": "object",
                      "properties": {
                        "user": {
                          "$ref": "#/components/schemas/user"
                        },
                        "session": {
                          "$ref": "#/components/schemas/session"
                        }
                      }
                    }
                  }
                }
              }
            }
          },
          "400": {
            "$ref": "#/components/responses/400"
          },
          "401": {
            "$ref": "#/components/responses/401"
          },
          "500": {
            "$ref": "#/components/responses/500"
          }
        }
      }
    },
    "/auth/logout": {
      "post": {
        "tags": [
          "Auth"
        ],
        "summary": "Logout user",
        "description": "Invalidates the user's session",
        "operationId": "Logout",
        "security": [
          {
            "bearerAuth": []
          }
        ],
        "responses": {
          "204": {
            "description": "Successfully logged out. No content."
          },
          "401": {
            "$ref": "#/components/responses/401"
          },
          "500": {
            "$ref": "#/components/responses/500"
          }
        }
      }
    },
    "/auth/refresh-session": {
      "post": {
        "tags": [
          "Auth"
        ],
        "summary": "Refresh access and refresh tokens",
        "description": "Generates a new pair of tokens using a valid refresh token",
        "operationId": "RefreshSession",
        "security": [
          {
            "bearerAuth": []
          }
        ],
        "responses": {
          "200": {
            "description": "Successfully refreshed a session!",
            "content": {
              "application/json": {
                "schema": {
                  "type": "object",
                  "required": [
                    "status",
                    "message",
                    "data"
                  ],
                  "properties": {
                    "status": {
                      "type": "integer",
                      "example": 200
                    },
                    "message": {
                      "type": "string",
                      "example": "Successfully refreshed a session!"
                    },
                    "data": {
                      "$ref": "#/components/schemas/session"
                    }
                  }
                }
              }
            }
          },
          "400": {
            "$ref": "#/components/responses/400"
          },
          "401": {
            "$ref": "#/components/responses/401"
          },
          "500": {
            "$ref": "#/components/responses/500"
          }
        }
      }
    },
    "/users": {
      "get": {
        "tags": [
          "Users"
        ],
        "summary": "Get all users",
        "description": "Retrieve a paginated list of all users",
        "operationId": "getAllUsers",
        "security": [
          {
            "bearerAuth": []
          }
        ],
        "parameters": [
          {
            "in": "query",
            "name": "page",
            "schema": {
              "type": "integer",
              "default": 1
            },
            "description": "Page number"
          },
          {
            "in": "query",
            "name": "perPage",
            "schema": {
              "type": "integer",
              "default": 10
            },
            "description": "Number of items per page"
          }
        ],
        "responses": {
          "200": {
            "description": "Successfully retrieved users",
            "content": {
              "application/json": {
                "schema": {
                  "type": "object",
                  "properties": {
                    "status": {
                      "type": "integer",
                      "example": 200
                    },
                    "message": {
                      "type": "string",
                      "example": "Successfully found users!"
                    },
                    "data": {
                      "type": "object",
                      "properties": {
                        "data": {
                          "type": "array",
                          "items": {
                            "$ref": "#/components/schemas/user"
                          }
                        },
                        "page": {
                          "type": "integer",
                          "example": 1
                        },
                        "perPage": {
                          "type": "integer",
                          "example": 10
                        },
                        "totalPages": {
                          "type": "integer",
                          "example": 5
                        },
                        "totalItems": {
                          "type": "integer",
                          "example": 42
                        },
                        "hasPreviousPage": {
                          "type": "boolean",
                          "example": true
                        },
                        "hasNextPage": {
                          "type": "boolean",
                          "example": true
                        }
                      }
                    }
                  }
                }
              }
            }
          },
          "400": {
            "$ref": "#/components/responses/400"
          },
          "500": {
            "$ref": "#/components/responses/500"
          }
        }
      }
    },
    "/users/{userId}": {
      "get": {
        "tags": [
          "Users"
        ],
        "summary": "Get a user by id",
        "description": "Retrieve a single user by their unique id",
        "operationId": "getUserById",
        "security": [
          {
            "bearerAuth": []
          }
        ],
        "parameters": [
          {
            "in": "path",
            "name": "userId",
            "required": true,
            "schema": {
              "type": "string"
            },
            "description": "User id"
          }
        ],
        "responses": {
          "200": {
            "description": "Successfully retrieved user",
            "content": {
              "application/json": {
                "schema": {
                  "type": "object",
                  "properties": {
                    "status": {
                      "type": "integer",
                      "example": 200
                    },
                    "message": {
                      "type": "string",
                      "example": "Successfully found user with id ...!"
                    },
                    "data": {
                      "$ref": "#/components/schemas/user"
                    }
                  }
                }
              }
            }
          },
          "404": {
            "description": "User not found",
            "content": {
              "application/json": {
                "schema": {
                  "type": "object",
                  "required": [
                    "status",
                    "message",
                    "data"
                  ],
                  "properties": {
                    "status": {
                      "type": "integer",
                      "example": 404
                    },
                    "message": {
                      "type": "string",
                      "example": "User not found"
                    },
                    "data": {
                      "type": "object",
                      "properties": {
                        "message": {
                          "type": "string",
                          "example": "User not found"
                        }
                      }
                    }
                  }
                }
              }
            }
          },
          "500": {
            "$ref": "#/components/responses/500"
          }
        }
      }
    },
    "/users/me": {
      "get": {
        "tags": [
          "Users"
        ],
        "summary": "Get current user",
        "description": "Retrieve the currently authenticated user's profile",
        "operationId": "getCurrentUser",
        "security": [
          {
            "bearerAuth": []
          }
        ],
        "responses": {
          "200": {
            "description": "Successfully retrieved current user",
            "content": {
              "application/json": {
                "schema": {
                  "type": "object",
                  "properties": {
                    "status": {
                      "type": "integer",
                      "example": 200
                    },
                    "message": {
                      "type": "string",
                      "example": "Current user retrieved successfully"
                    },
                    "data": {
                      "$ref": "#/components/schemas/user"
                    }
                  }
                }
              }
            }
          },
          "401": {
            "$ref": "#/components/responses/401"
          },
          "500": {
            "$ref": "#/components/responses/500"
          }
        }
      },
      "patch": {
        "tags": [
          "Users"
        ],
        "summary": "Update current user",
        "description": "Update fields of the authenticated user's profile",
        "operationId": "patchCurrentUser",
        "security": [
          {
            "bearerAuth": []
          }
        ],
        "requestBody": {
          "required": true,
          "content": {
            "multipart/form-data": {
              "schema": {
                "type": "object",
                "properties": {
                  "name": {
                    "type": "string"
                  },
                  "email": {
                    "type": "string"
                  },
                  "password": {
                    "type": "string"
                  },
                  "description": {
                    "type": "string"
                  }
                }
              }
            }
          }
        },
        "responses": {
          "200": {
            "description": "Successfully updated user",
            "content": {
              "application/json": {
                "schema": {
                  "type": "object",
                  "properties": {
                    "status": {
                      "type": "integer",
                      "example": 200
                    },
                    "message": {
                      "type": "string",
                      "example": "User updated successfully"
                    },
                    "data": {
                      "$ref": "#/components/schemas/user"
                    }
                  }
                }
              }
            }
          },
          "400": {
            "$ref": "#/components/responses/400"
          },
          "401": {
            "$ref": "#/components/responses/401"
          },
          "500": {
            "$ref": "#/components/responses/500"
          }
        }
      }
    },
    "/users/avatar": {
      "patch": {
        "tags": [
          "Users"
        ],
        "summary": "Update user avatar",
        "description": "Upload and update the authenticated user's avatar",
        "operationId": "updateUserAvatar",
        "security": [
          {
            "bearerAuth": []
          }
        ],
        "requestBody": {
          "required": true,
          "content": {
            "multipart/form-data": {
              "schema": {
                "type": "object",
                "properties": {
                  "avatar": {
                    "type": "string",
                    "format": "binary"
                  }
                }
              }
            }
          }
        },
        "responses": {
          "200": {
            "description": "Avatar updated successfully",
            "content": {
              "application/json": {
                "schema": {
                  "type": "object",
                  "properties": {
                    "status": {
                      "type": "integer",
                      "example": 200
                    },
                    "message": {
                      "type": "string",
                      "example": "Avatar updated successfully"
                    },
                    "data": {
                      "$ref": "#/components/schemas/user"
                    }
                  }
                }
              }
            }
          },
          "400": {
            "$ref": "#/components/responses/400"
          },
          "401": {
            "$ref": "#/components/responses/401"
          },
          "500": {
            "$ref": "#/components/responses/500"
          }
        }
      }
    },
    "/users/saved-articles/{articleId}": {
      "post": {
        "tags": [
          "Users"
        ],
        "summary": "Add article to saved list",
        "description": "Adds an article to the authenticated user's savedArticles",
        "operationId": "addSavedArticle",
        "security": [
          {
            "bearerAuth": []
          }
        ],
        "parameters": [
          {
            "in": "path",
            "name": "articleId",
            "required": true,
            "schema": {
              "type": "string"
            }
          }
        ],
        "responses": {
          "200": {
            "description": "Article added successfully",
            "content": {
              "application/json": {
                "schema": {
                  "type": "object",
                  "properties": {
                    "message": {
                      "type": "string",
                      "example": "Article added to saved list"
                    },
                    "savedArticles": {
                      "type": "array",
                      "items": {
                        "type": "string"
                      }
                    },
                    "favoriteCount": {
                      "type": "integer",
                      "example": 5
                    }
                  }
                }
              }
            }
          },
          "401": {
            "$ref": "#/components/responses/401"
          },
          "404": {
            "$ref": "#/components/responses/404"
          },
          "500": {
            "$ref": "#/components/responses/500"
          }
        }
      },
      "delete": {
        "tags": [
          "Users"
        ],
        "summary": "Remove article from saved list",
        "description": "Removes an article from the authenticated user's savedArticles",
        "operationId": "removeSavedArticle",
        "security": [
          {
            "bearerAuth": []
          }
        ],
        "parameters": [
          {
            "in": "path",
            "name": "articleId",
            "required": true,
            "schema": {
              "type": "string"
            }
          }
        ],
        "responses": {
          "200": {
            "description": "Article removed successfully",
            "content": {
              "application/json": {
                "schema": {
                  "type": "object",
                  "properties": {
                    "message": {
                      "type": "string",
                      "example": "Article removed from saved list"
                    },
                    "savedArticles": {
                      "type": "array",
                      "items": {
                        "type": "string"
                      }
                    },
                    "favoriteCount": {
                      "type": "integer",
                      "example": 4
                    }
                  }
                }
              }
            }
          },
          "401": {
            "$ref": "#/components/responses/401"
          },
          "500": {
            "$ref": "#/components/responses/500"
          }
        }
      }
    },
    "/stories": {
      "get": {
        "tags": [
          "Stories"
        ],
        "summary": "Get all stories",
        "description": "Retrieve a paginated list of all stories. Use query param `mine=true` to get user's own stories.",
        "operationId": "getAllStories",
        "security": [
          {
            "bearerAuth": []
          }
        ],
        "parameters": [
          {
            "in": "query",
            "name": "page",
            "schema": {
              "type": "integer",
              "default": 1
            },
            "description": "Page number"
          },
          {
            "in": "query",
            "name": "perPage",
            "schema": {
              "type": "integer",
              "default": 10
            },
            "description": "Items per page"
          },
          {
            "in": "query",
            "name": "category",
            "schema": {
              "type": "string"
            },
            "description": "Items per page"
          },
          {
            "in": "query",
            "name": "mine",
            "schema": {
              "type": "boolean",
              "default": false
            },
            "description": "If true, returns only user's own stories (requires authentication)"
          }
        ],
        "responses": {
          "200": {
            "description": "Successfully retrieved stories",
            "content": {
              "application/json": {
                "schema": {
                  "type": "object",
                  "properties": {
                    "status": {
                      "type": "integer",
                      "example": 200
                    },
                    "message": {
                      "type": "string",
                      "example": "Successfully found stories!"
                    },
                    "data": {
                      "type": "object",
                      "properties": {
                        "data": {
                          "type": "array",
                          "items": {
                            "$ref": "#/components/schemas/story"
                          }
                        },
                        "page": {
                          "type": "integer",
                          "example": 1
                        },
                        "perPage": {
                          "type": "integer",
                          "example": 9
                        },
                        "totalPages": {
                          "type": "integer",
                          "example": 5
                        },
                        "totalItems": {
                          "type": "integer",
                          "example": 42
                        },
                        "hasPreviousPage": {
                          "type": "boolean",
                          "example": true
                        },
                        "hasNextPage": {
                          "type": "boolean",
                          "example": true
                        }
                      }
                    }
                  }
                }
              }
            }
          },
          "400": {
            "$ref": "#/components/responses/400"
          },
          "401": {
            "$ref": "#/components/responses/401"
          },
          "500": {
            "$ref": "#/components/responses/500"
          }
        }
      },
      "post": {
        "tags": [
          "Stories"
        ],
        "summary": "Create a story",
        "description": "Upload a new story with an optional image. Requires authentication.",
        "operationId": "createStory",
        "security": [
          {
            "bearerAuth": []
          }
        ],
        "requestBody": {
          "required": true,
          "content": {
            "multipart/form-data": {
              "schema": {
                "type": "object",
                "required": [
                  "title",
                  "description",
                  "category"
                ],
                "properties": {
                  "storyImage": {
                    "type": "string",
                    "format": "binary",
                    "description": "Image file for the story"
                  },
                  "title": {
                    "type": "string"
                  },
                  "description": {
                    "type": "string"
                  },
                  "category": {
                    "type": "string"
                  }
                }
              }
            }
          }
        },
        "responses": {
          "201": {
            "description": "Story created successfully",
            "content": {
              "application/json": {
                "schema": {
                  "type": "object",
                  "properties": {
                    "status": {
                      "type": "integer",
                      "example": 201
                    },
                    "message": {
                      "type": "string",
                      "example": "Successfully created a story!"
                    },
                    "data": {
                      "$ref": "#/components/schemas/story"
                    }
                  }
                }
              }
            }
          },
          "400": {
            "$ref": "#/components/responses/400"
          },
          "401": {
            "$ref": "#/components/responses/401"
          },
          "500": {
            "$ref": "#/components/responses/500"
          }
        }
      }
    },
    "/stories/{storyId}": {
      "get": {
        "tags": [
          "Stories"
        ],
        "summary": "Get a story by ID",
        "description": "Retrieve a single story by its ID",
        "operationId": "getStoryById",
        "security": [
          {
            "bearerAuth": []
          }
        ],
        "parameters": [
          {
            "in": "path",
            "name": "storyId",
            "required": true,
            "schema": {
              "type": "string"
            },
            "description": "ID of the story"
          }
        ],
        "responses": {
          "200": {
            "description": "Successfully retrieved story",
            "content": {
              "application/json": {
                "schema": {
                  "type": "object",
                  "properties": {
                    "status": {
                      "type": "integer",
                      "example": 200
                    },
                    "message": {
                      "type": "string",
                      "example": "Successfully found story!"
                    },
                    "data": {
                      "$ref": "#/components/schemas/story"
                    }
                  }
                }
              }
            }
          },
          "400": {
            "$ref": "#/components/responses/400"
          },
          "404": {
            "description": "Story not found",
            "content": {
              "application/json": {
                "schema": {
                  "type": "object",
                  "required": [
                    "status",
                    "message",
                    "data"
                  ],
                  "properties": {
                    "status": {
                      "type": "integer",
                      "example": 404
                    },
                    "message": {
                      "type": "string",
                      "example": "Story not found"
                    },
                    "data": {
                      "type": "object",
                      "properties": {
                        "message": {
                          "type": "string",
                          "example": "Story not found"
                        }
                      }
                    }
                  }
                }
              }
            }
          },
          "500": {
            "$ref": "#/components/responses/500"
          }
        }
      },
      "patch": {
        "tags": [
          "Stories"
        ],
        "summary": "Update a story",
        "description": "Update a story by its ID. Requires authentication and ownership.",
        "operationId": "patchStory",
        "security": [
          {
            "bearerAuth": []
          }
        ],
        "parameters": [
          {
            "in": "path",
            "name": "storyId",
            "required": true,
            "schema": {
              "type": "string"
            },
            "description": "ID of the story"
          }
        ],
        "requestBody": {
          "required": true,
          "content": {
            "multipart/form-data": {
              "schema": {
                "type": "object",
                "properties": {
                  "storyImage": {
                    "type": "string",
                    "format": "binary",
                    "description": "Updated image for the story"
                  },
                  "title": {
                    "type": "string"
                  },
                  "description": {
                    "type": "string"
                  },
                  "category": {
                    "type": "string"
                  }
                }
              }
            }
          }
        },
        "responses": {
          "200": {
            "description": "Story updated successfully",
            "content": {
              "application/json": {
                "schema": {
                  "type": "object",
                  "properties": {
                    "status": {
                      "type": "integer",
                      "example": 200
                    },
                    "message": {
                      "type": "string",
                      "example": "Successfully updated the story!"
                    },
                    "data": {
                      "$ref": "#/components/schemas/story"
                    }
                  }
                }
              }
            }
          },
          "400": {
            "$ref": "#/components/responses/400"
          },
          "401": {
            "$ref": "#/components/responses/401"
          },
          "404": {
            "description": "Story not found or user does not have permission",
            "content": {
              "application/json": {
                "schema": {
                  "type": "object",
                  "required": [
                    "status",
                    "message",
                    "data"
                  ],
                  "properties": {
                    "status": {
                      "type": "integer",
                      "example": 404
                    },
                    "message": {
                      "type": "string",
                      "example": "Story not found or you don't have permission"
                    },
                    "data": {
                      "type": "object",
                      "properties": {
                        "message": {
                          "type": "string",
                          "example": "Story not found or you don't have permission"
                        }
                      }
                    }
                  }
                }
              }
            }
          },
          "500": {
            "$ref": "#/components/responses/500"
          }
        }
      },
      "delete": {
        "tags": [
          "Stories"
        ],
        "summary": "Delete a story",
        "description": "Delete a story by its ID. Requires authentication and ownership.",
        "operationId": "deleteStory",
        "security": [
          {
            "bearerAuth": []
          }
        ],
        "parameters": [
          {
            "in": "path",
            "name": "storyId",
            "required": true,
            "schema": {
              "type": "string"
            },
            "description": "ID of the story"
          }
        ],
        "responses": {
          "204": {
            "description": "Story deleted successfully, no content"
          },
          "400": {
            "$ref": "#/components/responses/400"
          },
          "404": {
            "description": "Story not found or user does not have permission",
            "content": {
              "application/json": {
                "schema": {
                  "type": "object",
                  "required": [
                    "status",
                    "message",
                    "data"
                  ],
                  "properties": {
                    "status": {
                      "type": "integer",
                      "example": 404
                    },
                    "message": {
                      "type": "string",
                      "example": "Story not found or you don't have permission"
                    },
                    "data": {
                      "type": "object",
                      "properties": {
                        "message": {
                          "type": "string",
                          "example": "Story not found or you don't have permission"
                        }
                      }
                    }
                  }
                }
              }
            }
          },
          "500": {
            "$ref": "#/components/responses/500"
          }
        }
      }
    },
    "/categories": {
      "get": {
        "tags": [
          "Categories"
        ],
        "summary": "Get all categories",
        "description": "Retrieve a paginated list of all categories",
        "operationId": "getAllCategories",
        "security": [
          {
            "bearerAuth": []
          }
        ],
        "parameters": [
          {
            "in": "query",
            "name": "page",
            "required": false,
            "schema": {
              "type": "integer",
              "default": 1
            },
            "description": "Page number for pagination"
          },
          {
            "in": "query",
            "name": "perPage",
            "required": false,
            "schema": {
              "type": "integer",
              "default": 10
            },
            "description": "Number of items per page"
          }
        ],
        "responses": {
          "200": {
            "description": "Successfully retrieved categories",
            "content": {
              "application/json": {
                "schema": {
                  "type": "object",
                  "properties": {
                    "status": {
                      "type": "integer",
                      "example": 200
                    },
                    "message": {
                      "type": "string",
                      "example": "Successfully found categories!"
                    },
                    "data": {
                      "type": "object",
                      "properties": {
                        "data": {
                          "type": "array",
                          "items": {
                            "$ref": "#/components/schemas/category"
                          }
                        },
                        "page": {
                          "type": "integer",
                          "example": 1
                        },
                        "perPage": {
                          "type": "integer",
                          "example": 10
                        },
                        "totalPages": {
                          "type": "integer",
                          "example": 5
                        },
                        "totalItems": {
                          "type": "integer",
                          "example": 42
                        },
                        "hasPreviousPage": {
                          "type": "boolean",
                          "example": true
                        },
                        "hasNextPage": {
                          "type": "boolean",
                          "example": true
                        }
                      }
                    }
                  }
                }
              }
            }
          },
          "400": {
            "$ref": "#/components/responses/400"
          },
          "500": {
            "$ref": "#/components/responses/500"
          }
        }
      }
    },
    "/categories/{categoryId}": {
      "get": {
        "tags": [
          "Categories"
        ],
        "summary": "Get category by ID",
        "description": "Retrieve a specific category by its unique ID",
        "operationId": "getCategoryById",
        "security": [
          {
            "bearerAuth": []
          }
        ],
        "parameters": [
          {
            "in": "path",
            "name": "categoryId",
            "required": true,
            "schema": {
              "type": "string"
            },
            "description": "Category ID"
          }
        ],
        "responses": {
          "200": {
            "description": "Successfully retrieved category",
            "content": {
              "application/json": {
                "schema": {
                  "type": "object",
                  "properties": {
                    "status": {
                      "type": "integer",
                      "example": 200
                    },
                    "message": {
                      "type": "string",
                      "example": "Successfully found category"
                    },
                    "data": {
                      "$ref": "#/components/schemas/category"
                    }
                  }
                }
              }
            }
          },
          "400": {
            "$ref": "#/components/responses/400"
          },
          "404": {
            "description": "Category not found",
            "content": {
              "application/json": {
                "schema": {
                  "type": "object",
                  "properties": {
                    "status": {
                      "type": "integer",
                      "example": 404
                    },
                    "message": {
                      "type": "string",
                      "example": "Category not found"
                    }
                  }
                }
              }
            }
          },
          "500": {
            "$ref": "#/components/responses/500"
          }
        }
      }
    }
  },
  "components": {
    "securitySchemes": {
      "bearerAuth": {
        "type": "http",
        "scheme": "bearer",
        "bearerFormat": "JWT"
      }
    },
    "schemas": {
      "user": {
        "type": "object",
        "properties": {
          "name": {
            "type": "string",
            "description": "User name",
            "example": "John Dou"
          },
          "email": {
            "type": "string",
            "description": "User email",
            "example": "example@gmail.com"
          },
          "password": {
            "type": "string",
            "description": "User password",
            "example": "Secret123"
          },
          "avatarUrl": {
            "type": "string",
            "description": "url to user avatar image",
            "example": "https://res.cloudinary.com/..."
          },
          "avatarPublicId": {
            "type": "string",
            "description": "id to your cloudinary avatar",
            "example": "asdj123123a"
          },
          "articlesAmount": {
            "type": "number",
            "description": "amount of your articles",
            "example": 1
          },
          "description": {
            "type": "string",
            "description": "your profile description",
            "example": "I`m a traveler John and I..."
          },
          "savedArticles": {
            "type": "array",
            "description": "List of saved story IDs",
            "items": {
              "type": "string"
            },
            "example": [
              "68fb50...",
              "68fb22..."
            ]
          },
          "createdAt": {
            "type": "string",
            "format": "date-time",
            "example": "2024-05-08T16:12:14.954173"
          },
          "updatedAt": {
            "type": "string",
            "format": "date-time",
            "example": "2024-05-08T16:12:14.954173"
          }
        }
      },
      "session": {
        "type": "object",
        "properties": {
          "_id": {
            "type": "string",
            "description": "Session id",
            "example": "68e5759deb0a7653b7151792"
          },
          "userId": {
            "type": "string",
            "description": "Session user id",
            "example": "68e56ee81d5e513eb335c0c2"
          },
          "accessToken": {
            "type": "string",
            "description": "Session access token",
            "example": "sadfjdke14Sasdkl"
          },
          "refreshToken": {
            "type": "string",
            "description": "Session refresh token",
            "example": "sadfjdke14Sasdkl"
          },
          "accessTokenValidUntil": {
            "type": "string",
            "format": "date-time",
            "description": "Date expiring of access token",
            "example": "2025-11-16T14:25:19.025Z"
          },
          "refreshTokenValidUntil": {
            "type": "string",
            "format": "date-time",
            "description": "Date expiring of refresh token",
            "example": "2025-11-16T14:25:19.025Z"
          },
          "createdAt": {
            "type": "string",
            "format": "date-time",
            "example": "2024-05-08T16:12:14.954173"
          },
          "updatedAt": {
            "type": "string",
            "format": "date-time",
            "example": "2024-05-08T16:12:14.954173"
          }
        }
      },
      "story": {
        "type": "object",
        "properties": {
          "_id": {
            "type": "string",
            "description": "story id",
            "example": "68e5759deb0a7653b7151792"
          },
          "img": {
            "type": "string",
            "description": "url to story image",
            "example": "https://res.cloudinary.com/..."
          },
          "title": {
            "type": "string",
            "description": "story title",
            "example": "my trip to Paris"
          },
          "description": {
            "type": "string",
            "description": "description of story",
            "example": "when I was there..."
          },
          "category": {
            "type": "string",
            "description": "category Id",
            "example": "68fb50c80ae91338641121f7"
          },
          "ownerId": {
            "type": "string",
            "description": "owner user Id",
            "example": "68fb50c80ae91338641121f7"
          },
          "date": {
            "type": "string",
            "description": "story publication date",
            "example": "2024-05-08T16:12:14.954173"
          },
          "favoriteCount": {
            "type": "number",
            "description": "Number of users who saved this story",
            "example": 100
          },
          "createdAt": {
            "type": "string",
            "format": "date-time",
            "example": "2024-05-08T16:12:14.954173"
          },
          "updatedAt": {
            "type": "string",
            "format": "date-time",
            "example": "2024-05-08T16:12:14.954173"
          }
        }
      },
      "category": {
        "type": "object",
        "properties": {
          "_id": {
            "type": "string",
            "description": "Category id",
            "example": "65ca67e7ae7f10c88b598384"
          },
          "name": {
            "type": "string",
            "description": "Category name",
            "example": "Africa"
          }
        }
      }
    },
    "responses": {
      "400": {
        "description": "Internal Server Error",
        "content": {
          "application/json": {
            "schema": {
              "type": "object",
              "properties": {
                "status": {
                  "type": "integer",
                  "example": 400
                },
                "message": {
                  "type": "string",
                  "example": "Something went wrong"
                },
                "data": {
                  "type": "object",
                  "properties": {
                    "message": {
                      "type": "string",
                      "example": "Internal Server Error"
                    }
                  }
                }
              }
            }
          }
        }
      },
      "401": {
        "description": "Unauthorized Error",
        "content": {
          "application/json": {
            "schema": {
              "type": "object",
              "properties": {
                "status": {
                  "type": "integer",
                  "example": 401
                },
                "message": {
                  "type": "string",
                  "example": "Unauthorized Error"
                }
              }
            }
          }
        }
      },
      "404": {
        "description": "Route not found",
        "content": {
          "application/json": {
            "schema": {
              "type": "object",
              "required": [
                "status",
                "message",
                "data"
              ],
              "properties": {
                "status": {
                  "type": "integer",
                  "example": 404
                },
                "message": {
                  "type": "string",
                  "example": "NotFoundError"
                },
                "data": {
                  "type": "object",
                  "properties": {
                    "message": {
                      "type": "string",
                      "example": "Route not found"
                    }
                  }
                }
              }
            }
          }
        }
      },
      "500": {
        "description": "Internal Server Error",
        "content": {
          "application/json": {
            "schema": {
              "type": "object",
              "required": [
                "status",
                "message"
              ],
              "properties": {
                "status": {
                  "type": "integer",
                  "example": 500
                },
                "message": {
                  "type": "string",
                  "example": "Something went wrong"
                },
                "data": {
                  "type": "object",
                  "properties": {
                    "message": {
                      "type": "string",
                      "example": "Internal Server Error"
                    }
                  }
                }
              }
            }
          }
        }
      }
    }
  }
}